wenxian/__init__.py
wenxian/__main__.py
wenxian/from_identifier.py
wenxian/identifier.py
wenxian/logger.py
wenxian/py.typed
wenxian/reference.py
wenxian/feeder/__init__.py
wenxian/feeder/arxiv.py
wenxian/feeder/chemrxiv.py
wenxian/feeder/crossref.py
wenxian/feeder/feeder.py
wenxian/feeder/pubmed.py
wenxian/feeder/semanticscholar.py
wenxian/feeder/session.py
wenxian-0.2.0.dist-info/licenses/LICENSE
wenxian-0.2.0.dist-info/METADATA
wenxian-0.2.0.dist-info/WHEEL
wenxian-0.2.0.dist-info/entry_points.txt
wenxian-0.2.0.dist-info/top_level.txt
wenxian-0.2.0.dist-info/RECORD
