Metadata-Version: 2.4
Name: wenxian
Version: 0.2.0
Summary: Generate references.
Author-email: Jinzhe Zeng <jinzhe.zeng@ustc.edu.cn>
License:                    GNU LESSER GENERAL PUBLIC LICENSE
Project-URL: repository, https://github.com/njzjz/wenxian
Keywords: bib
Classifier: Programming Language :: Python :: 3.8
Classifier: Programming Language :: Python :: 3.9
Classifier: Programming Language :: Python :: 3.10
Classifier: Programming Language :: Python :: 3.11
Classifier: Programming Language :: Python :: 3.12
Classifier: Operating System :: POSIX :: Linux
Classifier: Operating System :: MacOS :: MacOS X
Classifier: Operating System :: Microsoft :: Windows
Classifier: License :: OSI Approved :: GNU Lesser General Public License v3 (LGPLv3)
Requires-Python: >=3.8
License-File: LICENSE
Requires-Dist: requests
Requires-Dist: pylatexenc
Requires-Dist: unidecode
Requires-Dist: pyiso4
Requires-Dist: requests-ratelimiter
Requires-Dist: pyrate-limiter
Provides-Extra: test
Requires-Dist: pytest; extra == "test"
Requires-Dist: pytest-cov; extra == "test"
Dynamic: license-file
